auto_aws_sso/__init__.py
auto_aws_sso/authorize_sso.py
auto_aws_sso/cli.py
auto_aws_sso/constant.py
auto_aws_sso/exception.py
auto_aws_sso-1.0.1.dist-info/METADATA
auto_aws_sso-1.0.1.dist-info/WHEEL
auto_aws_sso-1.0.1.dist-info/entry_points.txt
auto_aws_sso-1.0.1.dist-info/licenses/LICENSE
auto_aws_sso-1.0.1.dist-info/RECORD
