Metadata-Version: 2.4
Name: auto-aws-sso
Version: 1.0.1
Summary: Fuck AWS SSO.
Project-URL: Homepage, https://github.com/nikhilbadyal/auto-aws-sso
Project-URL: Bug Tracker, https://github.com/nikhilbadyal/auto-aws-sso/issues
Project-URL: Repository, https://github.com/nikhilbadyal/auto-aws-sso.git
Author-email: Nikhil Badyal <nikhill773384@gmail.com>
License:                                  Apache License
License-File: LICENSE
Keywords: aws,sso
Classifier: Development Status :: 5 - Production/Stable
Classifier: Environment :: Console
Classifier: Intended Audience :: Developers
Classifier: Intended Audience :: System Administrators
Classifier: License :: OSI Approved :: Apache Software License
Classifier: Programming Language :: Python :: 3.8
Classifier: Programming Language :: Python :: 3.9
Classifier: Programming Language :: Python :: 3.10
Classifier: Programming Language :: Python :: 3.11
Classifier: Programming Language :: Python :: 3.12
Classifier: Topic :: Internet
Classifier: Topic :: System :: Systems Administration
Classifier: Topic :: Utilities
Classifier: Typing :: Typed
Requires-Python: >=3.8
Requires-Dist: click
Requires-Dist: loguru
Requires-Dist: mypy-extensions
Requires-Dist: python-dateutil
Requires-Dist: selenium
Provides-Extra: dev
Requires-Dist: hatch; extra == 'dev'
Requires-Dist: hatch-requirements-txt; extra == 'dev'
Requires-Dist: pre-commit; extra == 'dev'
Requires-Dist: tbump; extra == 'dev'
